{
  "date": "2026-06-22",
  "fetchedAt": "2026-06-22T21:18:42.013860+00:00",
  "games": [
    {
      "gamePk": 824261,
      "gameTimeUTC": "2026-06-22T22:10:00Z",
      "gameTimeET": "6:10 PM ET",
      "lineupDropET": "2:40 PM ET",
      "lineupComplete": true,
      "homeTeam": "Detroit Tigers",
      "awayTeam": "New York Yankees",
      "venue": "Comerica Park",
      "ballparkKey": "Tigers",
      "topInning": {
        "teamBatting": "New York Yankees",
        "teamPitching": "Detroit Tigers",
        "pitcher": {
          "name": "Framber Valdez",
          "id": 664285,
          "pitchHand": "L"
        },
        "lineup": [
          {
            "name": "Amed Rosario",
            "id": 642708,
            "batSide": "R",
            "position": "3B"
          },
          {
            "name": "Ben Rice",
            "id": 700250,
            "batSide": "L",
            "position": "DH"
          },
          {
            "name": "Paul Goldschmidt",
            "id": 502671,
            "batSide": "R",
            "position": "1B"
          },
          {
            "name": "Cody Bellinger",
            "id": 641355,
            "batSide": "L",
            "position": "CF"
          },
          {
            "name": "Anthony Volpe",
            "id": 683011,
            "batSide": "R",
            "position": "SS"
          },
          {
            "name": "Jazz Chisholm Jr.",
            "id": 665862,
            "batSide": "L",
            "position": "2B"
          },
          {
            "name": "Jasson Dom\u00ednguez",
            "id": 691176,
            "batSide": "S",
            "position": "RF"
          },
          {
            "name": "Jos\u00e9 Caballero",
            "id": 676609,
            "batSide": "R",
            "position": "LF"
          },
          {
            "name": "Ali S\u00e1nchez",
            "id": 645305,
            "batSide": "R",
            "position": "C"
          }
        ],
        "gameId": "NYY/DET - Top 1"
      },
      "botInning": {
        "teamBatting": "Detroit Tigers",
        "teamPitching": "New York Yankees",
        "pitcher": {
          "name": "Gerrit Cole",
          "id": 543037,
          "pitchHand": "R"
        },
        "lineup": [
          {
            "name": "Kevin McGonigle",
            "id": 805808,
            "batSide": "L",
            "position": "3B"
          },
          {
            "name": "Dillon Dingler",
            "id": 693307,
            "batSide": "R",
            "position": "C"
          },
          {
            "name": "Kerry Carpenter",
            "id": 681481,
            "batSide": "L",
            "position": "RF"
          },
          {
            "name": "Riley Greene",
            "id": 682985,
            "batSide": "L",
            "position": "LF"
          },
          {
            "name": "Spencer Torkelson",
            "id": 679529,
            "batSide": "R",
            "position": "1B"
          },
          {
            "name": "Colt Keith",
            "id": 690993,
            "batSide": "L",
            "position": "DH"
          },
          {
            "name": "James Outman",
            "id": 681546,
            "batSide": "L",
            "position": "CF"
          },
          {
            "name": "Hao-Yu  Lee",
            "id": 701678,
            "batSide": "R",
            "position": "2B"
          },
          {
            "name": "Zach McKinstry",
            "id": 656716,
            "batSide": "L",
            "position": "SS"
          }
        ],
        "gameId": "NYY/DET - Bot 1"
      },
      "odds": {
        "draftkings": {
          "top": {
            "oddsPosted": true,
            "noOdds": 135,
            "yesOdds": -190,
            "impliedNSFI": 0.4255,
            "source": "draftkings_nash"
          },
          "bot": {
            "oddsPosted": true,
            "noOdds": 210,
            "yesOdds": -295,
            "impliedNSFI": 0.3226,
            "source": "draftkings_nash"
          }
        }
      }
    },
    {
      "gamePk": 822964,
      "gameTimeUTC": "2026-06-22T22:40:00Z",
      "gameTimeET": "6:40 PM ET",
      "lineupDropET": "3:10 PM ET",
      "lineupComplete": true,
      "homeTeam": "Tampa Bay Rays",
      "awayTeam": "Kansas City Royals",
      "venue": "Tropicana Field",
      "ballparkKey": "Rays",
      "topInning": {
        "teamBatting": "Kansas City Royals",
        "teamPitching": "Tampa Bay Rays",
        "pitcher": {
          "name": "Drew Rasmussen",
          "id": 656876,
          "pitchHand": "R"
        },
        "lineup": [
          {
            "name": "Carter Jensen",
            "id": 695600,
            "batSide": "L",
            "position": "C"
          },
          {
            "name": "Maikel Garcia",
            "id": 672580,
            "batSide": "R",
            "position": "SS"
          },
          {
            "name": "Jac Caglianone",
            "id": 695506,
            "batSide": "L",
            "position": "1B"
          },
          {
            "name": "Salvador Perez",
            "id": 521692,
            "batSide": "R",
            "position": "DH"
          },
          {
            "name": "Michael Massey",
            "id": 686681,
            "batSide": "L",
            "position": "2B"
          },
          {
            "name": "Lane Thomas",
            "id": 657041,
            "batSide": "R",
            "position": "CF"
          },
          {
            "name": "John Rave",
            "id": 670231,
            "batSide": "L",
            "position": "RF"
          },
          {
            "name": "Nick Loftin",
            "id": 679845,
            "batSide": "R",
            "position": "3B"
          },
          {
            "name": "Isaac Collins",
            "id": 686555,
            "batSide": "S",
            "position": "LF"
          }
        ],
        "gameId": "KC/TB - Top 1"
      },
      "botInning": {
        "teamBatting": "Tampa Bay Rays",
        "teamPitching": "Kansas City Royals",
        "pitcher": {
          "name": "Michael Wacha",
          "id": 608379,
          "pitchHand": "R"
        },
        "lineup": [
          {
            "name": "Yandy D\u00edaz",
            "id": 650490,
            "batSide": "R",
            "position": "DH"
          },
          {
            "name": "Jonny DeLuca",
            "id": 676356,
            "batSide": "R",
            "position": "CF"
          },
          {
            "name": "Jonathan Aranda",
            "id": 666018,
            "batSide": "L",
            "position": "1B"
          },
          {
            "name": "Junior Caminero",
            "id": 691406,
            "batSide": "R",
            "position": "3B"
          },
          {
            "name": "Ryan Vilade",
            "id": 668723,
            "batSide": "R",
            "position": "RF"
          },
          {
            "name": "Chandler Simpson",
            "id": 802415,
            "batSide": "L",
            "position": "LF"
          },
          {
            "name": "Ben Williamson",
            "id": 810938,
            "batSide": "R",
            "position": "SS"
          },
          {
            "name": "Nick Fortes",
            "id": 663743,
            "batSide": "R",
            "position": "C"
          },
          {
            "name": "Richie Palacios",
            "id": 680700,
            "batSide": "L",
            "position": "2B"
          }
        ],
        "gameId": "KC/TB - Bot 1"
      },
      "odds": {
        "draftkings": {
          "top": {
            "oddsPosted": true,
            "noOdds": 255,
            "yesOdds": -370,
            "impliedNSFI": 0.2817,
            "source": "draftkings_nash"
          },
          "bot": {
            "oddsPosted": true,
            "noOdds": 105,
            "yesOdds": -145,
            "impliedNSFI": 0.4878,
            "source": "draftkings_nash"
          }
        }
      }
    },
    {
      "gamePk": 823851,
      "gameTimeUTC": "2026-06-22T22:40:00Z",
      "gameTimeET": "6:40 PM ET",
      "lineupDropET": "3:10 PM ET",
      "lineupComplete": true,
      "homeTeam": "Miami Marlins",
      "awayTeam": "Texas Rangers",
      "venue": "loanDepot park",
      "ballparkKey": "Marlins",
      "topInning": {
        "teamBatting": "Texas Rangers",
        "teamPitching": "Miami Marlins",
        "pitcher": {
          "name": "Tyler Phillips",
          "id": 663969,
          "pitchHand": "R"
        },
        "lineup": [
          {
            "name": "Joc Pederson",
            "id": 592626,
            "batSide": "L",
            "position": "DH"
          },
          {
            "name": "Wyatt Langford",
            "id": 694671,
            "batSide": "R",
            "position": "CF"
          },
          {
            "name": "Josh Jung",
            "id": 673962,
            "batSide": "R",
            "position": "3B"
          },
          {
            "name": "Brandon Nimmo",
            "id": 607043,
            "batSide": "L",
            "position": "RF"
          },
          {
            "name": "Jake Burger",
            "id": 669394,
            "batSide": "R",
            "position": "1B"
          },
          {
            "name": "Ezequiel Duran",
            "id": 677649,
            "batSide": "R",
            "position": "SS"
          },
          {
            "name": "Alejandro Osuna",
            "id": 696030,
            "batSide": "L",
            "position": "LF"
          },
          {
            "name": "Elias D\u00edaz",
            "id": 553869,
            "batSide": "R",
            "position": "C"
          },
          {
            "name": "Nicky Lopez",
            "id": 670032,
            "batSide": "L",
            "position": "2B"
          }
        ],
        "gameId": "TEX/MIA - Top 1"
      },
      "botInning": {
        "teamBatting": "Miami Marlins",
        "teamPitching": "Texas Rangers",
        "pitcher": {
          "name": "Tyler Alexander",
          "id": 641302,
          "pitchHand": "L"
        },
        "lineup": [
          {
            "name": "Heriberto Hern\u00e1ndez",
            "id": 681715,
            "batSide": "R",
            "position": "LF"
          },
          {
            "name": "Otto Lopez",
            "id": 672640,
            "batSide": "R",
            "position": "SS"
          },
          {
            "name": "Kyle Stowers",
            "id": 669065,
            "batSide": "L",
            "position": "1B"
          },
          {
            "name": "Xavier Edwards",
            "id": 669364,
            "batSide": "S",
            "position": "2B"
          },
          {
            "name": "Jakob Marsee",
            "id": 805300,
            "batSide": "L",
            "position": "CF"
          },
          {
            "name": "Esteury Ruiz",
            "id": 665923,
            "batSide": "R",
            "position": "RF"
          },
          {
            "name": "Griffin Conine",
            "id": 665052,
            "batSide": "L",
            "position": "DH"
          },
          {
            "name": "Javier Sanoja",
            "id": 691594,
            "batSide": "R",
            "position": "3B"
          },
          {
            "name": "Joe Mack",
            "id": 691788,
            "batSide": "L",
            "position": "C"
          }
        ],
        "gameId": "TEX/MIA - Bot 1"
      },
      "odds": {
        "draftkings": {
          "top": {
            "oddsPosted": true,
            "noOdds": 135,
            "yesOdds": -185,
            "impliedNSFI": 0.4255,
            "source": "draftkings_nash"
          },
          "bot": {
            "oddsPosted": true,
            "noOdds": 130,
            "yesOdds": -175,
            "impliedNSFI": 0.4348,
            "source": "draftkings_nash"
          }
        }
      }
    },
    {
      "gamePk": 822720,
      "gameTimeUTC": "2026-06-22T22:45:00Z",
      "gameTimeET": "6:45 PM ET",
      "lineupDropET": "3:15 PM ET",
      "lineupComplete": true,
      "homeTeam": "Washington Nationals",
      "awayTeam": "Philadelphia Phillies",
      "venue": "Nationals Park",
      "ballparkKey": "Nationals",
      "topInning": {
        "teamBatting": "Philadelphia Phillies",
        "teamPitching": "Washington Nationals",
        "pitcher": {
          "name": "Foster Griffin",
          "id": 656492,
          "pitchHand": "L"
        },
        "lineup": [
          {
            "name": "Trea Turner",
            "id": 607208,
            "batSide": "R",
            "position": "SS"
          },
          {
            "name": "Kyle Schwarber",
            "id": 656941,
            "batSide": "L",
            "position": "DH"
          },
          {
            "name": "Bryce Harper",
            "id": 547180,
            "batSide": "L",
            "position": "1B"
          },
          {
            "name": "Alec Bohm",
            "id": 664761,
            "batSide": "R",
            "position": "3B"
          },
          {
            "name": "Edmundo Sosa",
            "id": 624641,
            "batSide": "R",
            "position": "LF"
          },
          {
            "name": "Brandon Marsh",
            "id": 669016,
            "batSide": "L",
            "position": "RF"
          },
          {
            "name": "Derek Hill",
            "id": 656537,
            "batSide": "R",
            "position": "CF"
          },
          {
            "name": "Bryson Stott",
            "id": 681082,
            "batSide": "L",
            "position": "2B"
          },
          {
            "name": "Rafael March\u00e1n",
            "id": 665561,
            "batSide": "S",
            "position": "C"
          }
        ],
        "gameId": "PHI/WSH - Top 1"
      },
      "botInning": {
        "teamBatting": "Washington Nationals",
        "teamPitching": "Philadelphia Phillies",
        "pitcher": {
          "name": "Tim Mayza",
          "id": 641835,
          "pitchHand": "L"
        },
        "lineup": [
          {
            "name": "James Wood",
            "id": 695578,
            "batSide": "L",
            "position": "RF"
          },
          {
            "name": "Curtis Mead",
            "id": 678554,
            "batSide": "R",
            "position": "3B"
          },
          {
            "name": "Dylan Crews",
            "id": 686611,
            "batSide": "R",
            "position": "LF"
          },
          {
            "name": "CJ Abrams",
            "id": 682928,
            "batSide": "L",
            "position": "SS"
          },
          {
            "name": "Jacob Young",
            "id": 696285,
            "batSide": "R",
            "position": "CF"
          },
          {
            "name": "Daylen Lile",
            "id": 695734,
            "batSide": "L",
            "position": "DH"
          },
          {
            "name": "Keibert Ruiz",
            "id": 660688,
            "batSide": "S",
            "position": "C"
          },
          {
            "name": "Luis Garc\u00eda Jr.",
            "id": 671277,
            "batSide": "L",
            "position": "1B"
          },
          {
            "name": "Nasim Nu\u00f1ez",
            "id": 683083,
            "batSide": "S",
            "position": "2B"
          }
        ],
        "gameId": "PHI/WSH - Bot 1"
      },
      "odds": {
        "draftkings": {
          "top": {
            "oddsPosted": false
          },
          "bot": {
            "oddsPosted": true,
            "noOdds": 170,
            "yesOdds": -235,
            "impliedNSFI": 0.3704,
            "source": "draftkings_nash"
          }
        }
      }
    },
    {
      "gamePk": 822800,
      "gameTimeUTC": "2026-06-22T23:07:00Z",
      "gameTimeET": "7:07 PM ET",
      "lineupDropET": "3:37 PM ET",
      "lineupComplete": true,
      "homeTeam": "Toronto Blue Jays",
      "awayTeam": "Houston Astros",
      "venue": "Rogers Centre",
      "ballparkKey": "Blue Jays",
      "topInning": {
        "teamBatting": "Houston Astros",
        "teamPitching": "Toronto Blue Jays",
        "pitcher": {
          "name": "Dylan Cease",
          "id": 656302,
          "pitchHand": "R"
        },
        "lineup": [
          {
            "name": "Jeremy Pe\u00f1a",
            "id": 665161,
            "batSide": "R",
            "position": "SS"
          },
          {
            "name": "Yordan Alvarez",
            "id": 670541,
            "batSide": "L",
            "position": "LF"
          },
          {
            "name": "Christian Walker",
            "id": 572233,
            "batSide": "R",
            "position": "1B"
          },
          {
            "name": "Isaac Paredes",
            "id": 670623,
            "batSide": "R",
            "position": "DH"
          },
          {
            "name": "Jose Altuve",
            "id": 514888,
            "batSide": "R",
            "position": "2B"
          },
          {
            "name": "Yainer Diaz",
            "id": 673237,
            "batSide": "R",
            "position": "C"
          },
          {
            "name": "Joey Loperfido",
            "id": 694388,
            "batSide": "L",
            "position": "RF"
          },
          {
            "name": "Jake Meyers",
            "id": 676694,
            "batSide": "R",
            "position": "CF"
          },
          {
            "name": "Raynel Delgado",
            "id": 669384,
            "batSide": "L",
            "position": "3B"
          }
        ],
        "gameId": "HOU/TOR - Top 1"
      },
      "botInning": {
        "teamBatting": "Toronto Blue Jays",
        "teamPitching": "Houston Astros",
        "pitcher": {
          "name": "Hunter Brown",
          "id": 686613,
          "pitchHand": "R"
        },
        "lineup": [
          {
            "name": "George Springer",
            "id": 543807,
            "batSide": "R",
            "position": "DH"
          },
          {
            "name": "Nathan Lukes",
            "id": 664770,
            "batSide": "L",
            "position": "RF"
          },
          {
            "name": "Vladimir Guerrero Jr.",
            "id": 665489,
            "batSide": "R",
            "position": "1B"
          },
          {
            "name": "Alejandro Kirk",
            "id": 672386,
            "batSide": "R",
            "position": "C"
          },
          {
            "name": "Daulton Varsho",
            "id": 662139,
            "batSide": "L",
            "position": "CF"
          },
          {
            "name": "Kazuma Okamoto",
            "id": 672960,
            "batSide": "R",
            "position": "3B"
          },
          {
            "name": "Jes\u00fas S\u00e1nchez",
            "id": 660821,
            "batSide": "L",
            "position": "LF"
          },
          {
            "name": "Ernie Clement",
            "id": 676391,
            "batSide": "R",
            "position": "2B"
          },
          {
            "name": "Andr\u00e9s Gim\u00e9nez",
            "id": 665926,
            "batSide": "L",
            "position": "SS"
          }
        ],
        "gameId": "HOU/TOR - Bot 1"
      },
      "odds": {
        "draftkings": {
          "top": {
            "oddsPosted": true,
            "noOdds": 295,
            "yesOdds": -450,
            "impliedNSFI": 0.2532,
            "source": "draftkings_nash"
          },
          "bot": {
            "oddsPosted": true,
            "noOdds": 195,
            "yesOdds": -270,
            "impliedNSFI": 0.339,
            "source": "draftkings_nash"
          }
        }
      }
    },
    {
      "gamePk": 823613,
      "gameTimeUTC": "2026-06-22T23:10:00Z",
      "gameTimeET": "7:10 PM ET",
      "lineupDropET": "3:40 PM ET",
      "lineupComplete": true,
      "homeTeam": "New York Mets",
      "awayTeam": "Chicago Cubs",
      "venue": "Citi Field",
      "ballparkKey": "Mets",
      "topInning": {
        "teamBatting": "Chicago Cubs",
        "teamPitching": "New York Mets",
        "pitcher": {
          "name": "Kodai Senga",
          "id": 673540,
          "pitchHand": "R"
        },
        "lineup": [
          {
            "name": "Pete Crow-Armstrong",
            "id": 691718,
            "batSide": "L",
            "position": "CF"
          },
          {
            "name": "Alex Bregman",
            "id": 608324,
            "batSide": "R",
            "position": "3B"
          },
          {
            "name": "Michael Busch",
            "id": 683737,
            "batSide": "L",
            "position": "1B"
          },
          {
            "name": "Seiya Suzuki",
            "id": 673548,
            "batSide": "R",
            "position": "DH"
          },
          {
            "name": "Ian Happ",
            "id": 664023,
            "batSide": "S",
            "position": "LF"
          },
          {
            "name": "Matt Shaw",
            "id": 807713,
            "batSide": "R",
            "position": "RF"
          },
          {
            "name": "Nico Hoerner",
            "id": 663538,
            "batSide": "R",
            "position": "2B"
          },
          {
            "name": "Carson Kelly",
            "id": 608348,
            "batSide": "R",
            "position": "C"
          },
          {
            "name": "Dansby Swanson",
            "id": 621020,
            "batSide": "R",
            "position": "SS"
          }
        ],
        "gameId": "CHC/NYM - Top 1"
      },
      "botInning": {
        "teamBatting": "New York Mets",
        "teamPitching": "Chicago Cubs",
        "pitcher": {
          "name": "Shota Imanaga",
          "id": 684007,
          "pitchHand": "L"
        },
        "lineup": [
          {
            "name": "Carson Benge",
            "id": 701807,
            "batSide": "L",
            "position": "RF"
          },
          {
            "name": "Bo Bichette",
            "id": 666182,
            "batSide": "R",
            "position": "3B"
          },
          {
            "name": "Juan Soto",
            "id": 665742,
            "batSide": "L",
            "position": "LF"
          },
          {
            "name": "Marcus Semien",
            "id": 543760,
            "batSide": "R",
            "position": "2B"
          },
          {
            "name": "Mark Vientos",
            "id": 668901,
            "batSide": "R",
            "position": "1B"
          },
          {
            "name": "Eric Wagaman",
            "id": 676572,
            "batSide": "R",
            "position": "DH"
          },
          {
            "name": "Francisco Alvarez",
            "id": 682626,
            "batSide": "R",
            "position": "C"
          },
          {
            "name": "A.J. Ewing",
            "id": 805999,
            "batSide": "L",
            "position": "CF"
          },
          {
            "name": "Zack Short",
            "id": 670097,
            "batSide": "R",
            "position": "SS"
          }
        ],
        "gameId": "CHC/NYM - Bot 1"
      },
      "odds": {
        "draftkings": {
          "top": {
            "oddsPosted": true,
            "noOdds": 195,
            "yesOdds": -275,
            "impliedNSFI": 0.339,
            "source": "draftkings_nash"
          },
          "bot": {
            "oddsPosted": true,
            "noOdds": 150,
            "yesOdds": -210,
            "impliedNSFI": 0.4,
            "source": "draftkings_nash"
          }
        }
      }
    },
    {
      "gamePk": 824502,
      "gameTimeUTC": "2026-06-22T23:10:00Z",
      "gameTimeET": "7:10 PM ET",
      "lineupDropET": "3:40 PM ET",
      "lineupComplete": true,
      "homeTeam": "Cincinnati Reds",
      "awayTeam": "Milwaukee Brewers",
      "venue": "Great American Ball Park",
      "ballparkKey": "Reds",
      "topInning": {
        "teamBatting": "Milwaukee Brewers",
        "teamPitching": "Cincinnati Reds",
        "pitcher": {
          "name": "Brady Singer",
          "id": 663903,
          "pitchHand": "R"
        },
        "lineup": [
          {
            "name": "Christian Yelich",
            "id": 592885,
            "batSide": "L",
            "position": "DH"
          },
          {
            "name": "Jackson Chourio",
            "id": 694192,
            "batSide": "R",
            "position": "LF"
          },
          {
            "name": "Brice Turang",
            "id": 668930,
            "batSide": "L",
            "position": "2B"
          },
          {
            "name": "William Contreras",
            "id": 661388,
            "batSide": "R",
            "position": "C"
          },
          {
            "name": "Jake Bauers",
            "id": 641343,
            "batSide": "L",
            "position": "1B"
          },
          {
            "name": "Garrett Mitchell",
            "id": 669003,
            "batSide": "L",
            "position": "CF"
          },
          {
            "name": "Sal Frelick",
            "id": 686217,
            "batSide": "L",
            "position": "RF"
          },
          {
            "name": "Joey Ortiz",
            "id": 687401,
            "batSide": "R",
            "position": "SS"
          },
          {
            "name": "David Hamilton",
            "id": 666152,
            "batSide": "L",
            "position": "3B"
          }
        ],
        "gameId": "MIL/CIN - Top 1"
      },
      "botInning": {
        "teamBatting": "Cincinnati Reds",
        "teamPitching": "Milwaukee Brewers",
        "pitcher": {
          "name": "Brandon Woodruff",
          "id": 605540,
          "pitchHand": "R"
        },
        "lineup": [
          {
            "name": "Blake Dunn",
            "id": 694362,
            "batSide": "R",
            "position": "CF"
          },
          {
            "name": "JJ Bleday",
            "id": 668709,
            "batSide": "L",
            "position": "LF"
          },
          {
            "name": "Sal Stewart",
            "id": 701398,
            "batSide": "R",
            "position": "1B"
          },
          {
            "name": "Nathaniel Lowe",
            "id": 663993,
            "batSide": "L",
            "position": "DH"
          },
          {
            "name": "Spencer Steer",
            "id": 668715,
            "batSide": "R",
            "position": "2B"
          },
          {
            "name": "Eugenio Su\u00e1rez",
            "id": 553993,
            "batSide": "R",
            "position": "3B"
          },
          {
            "name": "Noelvi Marte",
            "id": 682622,
            "batSide": "R",
            "position": "RF"
          },
          {
            "name": "Tyler Stephenson",
            "id": 663886,
            "batSide": "R",
            "position": "C"
          },
          {
            "name": "Matt McLain",
            "id": 680574,
            "batSide": "R",
            "position": "SS"
          }
        ],
        "gameId": "MIL/CIN - Bot 1"
      },
      "odds": {
        "draftkings": {
          "top": {
            "oddsPosted": true,
            "noOdds": 175,
            "yesOdds": -245,
            "impliedNSFI": 0.3636,
            "source": "draftkings_nash"
          },
          "bot": {
            "oddsPosted": true,
            "noOdds": 225,
            "yesOdds": -320,
            "impliedNSFI": 0.3077,
            "source": "draftkings_nash"
          }
        }
      }
    },
    {
      "gamePk": 823692,
      "gameTimeUTC": "2026-06-22T23:40:00Z",
      "gameTimeET": "7:40 PM ET",
      "lineupDropET": "4:10 PM ET",
      "lineupComplete": true,
      "homeTeam": "Minnesota Twins",
      "awayTeam": "Los Angeles Dodgers",
      "venue": "Target Field",
      "ballparkKey": "Twins",
      "topInning": {
        "teamBatting": "Los Angeles Dodgers",
        "teamPitching": "Minnesota Twins",
        "pitcher": {
          "name": "Zebby Matthews",
          "id": 805673,
          "pitchHand": "R"
        },
        "lineup": [
          {
            "name": "Shohei Ohtani",
            "id": 660271,
            "batSide": "L",
            "position": "DH"
          },
          {
            "name": "Andy Pages",
            "id": 681624,
            "batSide": "R",
            "position": "CF"
          },
          {
            "name": "Freddie Freeman",
            "id": 518692,
            "batSide": "L",
            "position": "1B"
          },
          {
            "name": "Mookie Betts",
            "id": 605141,
            "batSide": "R",
            "position": "SS"
          },
          {
            "name": "Max Muncy",
            "id": 571970,
            "batSide": "L",
            "position": "3B"
          },
          {
            "name": "Kyle Tucker",
            "id": 663656,
            "batSide": "L",
            "position": "RF"
          },
          {
            "name": "Tommy Edman",
            "id": 669242,
            "batSide": "S",
            "position": "2B"
          },
          {
            "name": "Dalton Rushing",
            "id": 687221,
            "batSide": "L",
            "position": "C"
          },
          {
            "name": "Ryan Ward",
            "id": 669899,
            "batSide": "L",
            "position": "LF"
          }
        ],
        "gameId": "LAD/MIN - Top 1"
      },
      "botInning": {
        "teamBatting": "Minnesota Twins",
        "teamPitching": "Los Angeles Dodgers",
        "pitcher": {
          "name": "Eric Lauer",
          "id": 641778,
          "pitchHand": "L"
        },
        "lineup": [
          {
            "name": "Trevor Larnach",
            "id": 663616,
            "batSide": "L",
            "position": "LF"
          },
          {
            "name": "Byron Buxton",
            "id": 621439,
            "batSide": "R",
            "position": "CF"
          },
          {
            "name": "Kody Clemens",
            "id": 665019,
            "batSide": "L",
            "position": "RF"
          },
          {
            "name": "Josh Bell",
            "id": 605137,
            "batSide": "S",
            "position": "DH"
          },
          {
            "name": "Royce Lewis",
            "id": 668904,
            "batSide": "R",
            "position": "1B"
          },
          {
            "name": "Victor Caratini",
            "id": 605170,
            "batSide": "S",
            "position": "C"
          },
          {
            "name": "Brooks Lee",
            "id": 686797,
            "batSide": "S",
            "position": "3B"
          },
          {
            "name": "Luke Keaschall",
            "id": 807712,
            "batSide": "R",
            "position": "2B"
          },
          {
            "name": "Ryan Kreidler",
            "id": 668952,
            "batSide": "R",
            "position": "SS"
          }
        ],
        "gameId": "LAD/MIN - Bot 1"
      },
      "odds": {
        "draftkings": {
          "top": {
            "oddsPosted": true,
            "noOdds": 150,
            "yesOdds": -205,
            "impliedNSFI": 0.4,
            "source": "draftkings_nash"
          },
          "bot": {
            "oddsPosted": true,
            "noOdds": 230,
            "yesOdds": -330,
            "impliedNSFI": 0.303,
            "source": "draftkings_nash"
          }
        }
      }
    },
    {
      "gamePk": 824585,
      "gameTimeUTC": "2026-06-22T23:40:00Z",
      "gameTimeET": "7:40 PM ET",
      "lineupDropET": "4:10 PM ET",
      "lineupComplete": true,
      "homeTeam": "Chicago White Sox",
      "awayTeam": "Cleveland Guardians",
      "venue": "Rate Field",
      "ballparkKey": "White Sox",
      "topInning": {
        "teamBatting": "Cleveland Guardians",
        "teamPitching": "Chicago White Sox",
        "pitcher": {
          "name": "Anthony Kay",
          "id": 641743,
          "pitchHand": "L"
        },
        "lineup": [
          {
            "name": "Travis Bazzana",
            "id": 683953,
            "batSide": "L",
            "position": "2B"
          },
          {
            "name": "David Fry",
            "id": 681807,
            "batSide": "R",
            "position": "LF"
          },
          {
            "name": "Brayan Rocchio",
            "id": 677587,
            "batSide": "S",
            "position": "SS"
          },
          {
            "name": "Rhys Hoskins",
            "id": 656555,
            "batSide": "R",
            "position": "1B"
          },
          {
            "name": "Kyle Manzardo",
            "id": 700932,
            "batSide": "L",
            "position": "DH"
          },
          {
            "name": "Gabriel Arias",
            "id": 672356,
            "batSide": "R",
            "position": "3B"
          },
          {
            "name": "Stuart Fairchild",
            "id": 656413,
            "batSide": "R",
            "position": "RF"
          },
          {
            "name": "Austin Hedges",
            "id": 595978,
            "batSide": "R",
            "position": "C"
          },
          {
            "name": "Petey Halpin",
            "id": 690984,
            "batSide": "L",
            "position": "CF"
          }
        ],
        "gameId": "CLE/CWS - Top 1"
      },
      "botInning": {
        "teamBatting": "Chicago White Sox",
        "teamPitching": "Cleveland Guardians",
        "pitcher": {
          "name": "Gavin Williams",
          "id": 668909,
          "pitchHand": "R"
        },
        "lineup": [
          {
            "name": "Sam Antonacci",
            "id": 803011,
            "batSide": "L",
            "position": "LF"
          },
          {
            "name": "Miguel Vargas",
            "id": 678246,
            "batSide": "R",
            "position": "1B"
          },
          {
            "name": "Andrew Benintendi",
            "id": 643217,
            "batSide": "L",
            "position": "DH"
          },
          {
            "name": "Kyle Teel",
            "id": 691019,
            "batSide": "L",
            "position": "C"
          },
          {
            "name": "Colson Montgomery",
            "id": 695657,
            "batSide": "L",
            "position": "3B"
          },
          {
            "name": "Chase Meidroth",
            "id": 805367,
            "batSide": "R",
            "position": "2B"
          },
          {
            "name": "Braden Montgomery",
            "id": 695731,
            "batSide": "S",
            "position": "RF"
          },
          {
            "name": "Tristan Peters",
            "id": 671976,
            "batSide": "L",
            "position": "CF"
          },
          {
            "name": "Luisangel Acu\u00f1a",
            "id": 682668,
            "batSide": "R",
            "position": "SS"
          }
        ],
        "gameId": "CLE/CWS - Bot 1"
      },
      "odds": {
        "draftkings": {
          "top": {
            "oddsPosted": true,
            "noOdds": 180,
            "yesOdds": -255,
            "impliedNSFI": 0.3571,
            "source": "draftkings_nash"
          },
          "bot": {
            "oddsPosted": true,
            "noOdds": 275,
            "yesOdds": -425,
            "impliedNSFI": 0.2667,
            "source": "draftkings_nash"
          }
        }
      }
    },
    {
      "gamePk": 823040,
      "gameTimeUTC": "2026-06-22T23:45:00Z",
      "gameTimeET": "7:45 PM ET",
      "lineupDropET": "4:15 PM ET",
      "lineupComplete": true,
      "homeTeam": "St. Louis Cardinals",
      "awayTeam": "Arizona Diamondbacks",
      "venue": "Busch Stadium",
      "ballparkKey": "Cardinals",
      "topInning": {
        "teamBatting": "Arizona Diamondbacks",
        "teamPitching": "St. Louis Cardinals",
        "pitcher": {
          "name": "Andre Pallante",
          "id": 669467,
          "pitchHand": "R"
        },
        "lineup": [
          {
            "name": "Ketel Marte",
            "id": 606466,
            "batSide": "S",
            "position": "2B"
          },
          {
            "name": "Geraldo Perdomo",
            "id": 672695,
            "batSide": "S",
            "position": "SS"
          },
          {
            "name": "Corbin Carroll",
            "id": 682998,
            "batSide": "L",
            "position": "RF"
          },
          {
            "name": "Pavin Smith",
            "id": 656976,
            "batSide": "L",
            "position": "1B"
          },
          {
            "name": "Nolan Arenado",
            "id": 571448,
            "batSide": "R",
            "position": "3B"
          },
          {
            "name": "Adrian Del Castillo",
            "id": 680728,
            "batSide": "L",
            "position": "C"
          },
          {
            "name": "Lourdes Gurriel Jr.",
            "id": 666971,
            "batSide": "R",
            "position": "DH"
          },
          {
            "name": "Tommy Troy",
            "id": 694371,
            "batSide": "R",
            "position": "LF"
          },
          {
            "name": "Tim Tawa",
            "id": 694374,
            "batSide": "R",
            "position": "CF"
          }
        ],
        "gameId": "ARI/STL - Top 1"
      },
      "botInning": {
        "teamBatting": "St. Louis Cardinals",
        "teamPitching": "Arizona Diamondbacks",
        "pitcher": {
          "name": "Merrill Kelly",
          "id": 518876,
          "pitchHand": "R"
        },
        "lineup": [
          {
            "name": "JJ Wetherholt",
            "id": 802139,
            "batSide": "L",
            "position": "2B"
          },
          {
            "name": "Iv\u00e1n Herrera",
            "id": 671056,
            "batSide": "R",
            "position": "C"
          },
          {
            "name": "Alec Burleson",
            "id": 676475,
            "batSide": "L",
            "position": "1B"
          },
          {
            "name": "Jordan Walker",
            "id": 691023,
            "batSide": "R",
            "position": "RF"
          },
          {
            "name": "Lars Nootbaar",
            "id": 663457,
            "batSide": "L",
            "position": "LF"
          },
          {
            "name": "Masyn Winn",
            "id": 691026,
            "batSide": "R",
            "position": "SS"
          },
          {
            "name": "Jimmy Crooks",
            "id": 699625,
            "batSide": "L",
            "position": "DH"
          },
          {
            "name": "Blaze Jordan",
            "id": 691458,
            "batSide": "R",
            "position": "3B"
          },
          {
            "name": "Nathan Church",
            "id": 701675,
            "batSide": "L",
            "position": "CF"
          }
        ],
        "gameId": "ARI/STL - Bot 1"
      },
      "odds": {
        "draftkings": {
          "top": {
            "oddsPosted": true,
            "noOdds": 115,
            "yesOdds": -155,
            "impliedNSFI": 0.4651,
            "source": "draftkings_nash"
          },
          "bot": {
            "oddsPosted": true,
            "noOdds": -115,
            "yesOdds": -120,
            "impliedNSFI": 0.5349,
            "source": "draftkings_nash"
          }
        }
      }
    },
    {
      "gamePk": 824344,
      "gameTimeUTC": "2026-06-23T00:40:00Z",
      "gameTimeET": "8:40 PM ET",
      "lineupDropET": "5:10 PM ET",
      "lineupComplete": true,
      "homeTeam": "Colorado Rockies",
      "awayTeam": "Boston Red Sox",
      "venue": "Coors Field",
      "ballparkKey": "Rockies",
      "topInning": {
        "teamBatting": "Boston Red Sox",
        "teamPitching": "Colorado Rockies",
        "pitcher": {
          "name": "Ryan Feltner",
          "id": 663372,
          "pitchHand": "R"
        },
        "lineup": [
          {
            "name": "Mickey Gasper",
            "id": 681508,
            "batSide": "S",
            "position": "C"
          },
          {
            "name": "Ceddanne Rafaela",
            "id": 678882,
            "batSide": "R",
            "position": "CF"
          },
          {
            "name": "Wilyer Abreu",
            "id": 677800,
            "batSide": "L",
            "position": "RF"
          },
          {
            "name": "Willson Contreras",
            "id": 575929,
            "batSide": "R",
            "position": "1B"
          },
          {
            "name": "Jarren Duran",
            "id": 680776,
            "batSide": "L",
            "position": "LF"
          },
          {
            "name": "Caleb Durbin",
            "id": 702332,
            "batSide": "R",
            "position": "3B"
          },
          {
            "name": "Masataka Yoshida",
            "id": 807799,
            "batSide": "L",
            "position": "DH"
          },
          {
            "name": "Anthony Seigler",
            "id": 678011,
            "batSide": "S",
            "position": "2B"
          },
          {
            "name": "Marcelo Mayer",
            "id": 691785,
            "batSide": "L",
            "position": "SS"
          }
        ],
        "gameId": "BOS/COL - Top 1"
      },
      "botInning": {
        "teamBatting": "Colorado Rockies",
        "teamPitching": "Boston Red Sox",
        "pitcher": {
          "name": "Jake Bennett",
          "id": 687562,
          "pitchHand": "L"
        },
        "lineup": [
          {
            "name": "Willi Castro",
            "id": 650489,
            "batSide": "S",
            "position": "2B"
          },
          {
            "name": "Tyler Freeman",
            "id": 671289,
            "batSide": "R",
            "position": "RF"
          },
          {
            "name": "TJ Rumfield",
            "id": 681198,
            "batSide": "L",
            "position": "1B"
          },
          {
            "name": "Hunter Goodman",
            "id": 696100,
            "batSide": "R",
            "position": "C"
          },
          {
            "name": "Cole Carrigg",
            "id": 694249,
            "batSide": "S",
            "position": "CF"
          },
          {
            "name": "Jake McCarthy",
            "id": 664983,
            "batSide": "L",
            "position": "LF"
          },
          {
            "name": "Braxton Fulford",
            "id": 690924,
            "batSide": "R",
            "position": "DH"
          },
          {
            "name": "Ezequiel Tovar",
            "id": 678662,
            "batSide": "R",
            "position": "SS"
          },
          {
            "name": "Kyle Karros",
            "id": 691720,
            "batSide": "R",
            "position": "3B"
          }
        ],
        "gameId": "BOS/COL - Bot 1"
      },
      "odds": {
        "draftkings": {
          "top": {
            "oddsPosted": true,
            "noOdds": 145,
            "yesOdds": -200,
            "impliedNSFI": 0.4082,
            "source": "draftkings_nash"
          },
          "bot": {
            "oddsPosted": true,
            "noOdds": 115,
            "yesOdds": -160,
            "impliedNSFI": 0.4651,
            "source": "draftkings_nash"
          }
        }
      }
    },
    {
      "gamePk": 824016,
      "gameTimeUTC": "2026-06-23T01:38:00Z",
      "gameTimeET": "9:38 PM ET",
      "lineupDropET": "6:08 PM ET",
      "lineupComplete": false,
      "homeTeam": "Los Angeles Angels",
      "awayTeam": "Baltimore Orioles",
      "venue": "Angel Stadium",
      "ballparkKey": "Angels",
      "topInning": {
        "teamBatting": "Baltimore Orioles",
        "teamPitching": "Los Angeles Angels",
        "pitcher": {
          "name": "Sam Aldegheri",
          "id": 691951,
          "pitchHand": "L"
        },
        "lineup": [],
        "gameId": "BAL/LAA - Top 1"
      },
      "botInning": {
        "teamBatting": "Los Angeles Angels",
        "teamPitching": "Baltimore Orioles",
        "pitcher": {
          "name": "Kyle Bradish",
          "id": 680694,
          "pitchHand": "R"
        },
        "lineup": [
          {
            "name": "Zach Neto",
            "id": 687263,
            "batSide": "R",
            "position": "SS"
          },
          {
            "name": "Nolan Schanuel",
            "id": 694384,
            "batSide": "L",
            "position": "1B"
          },
          {
            "name": "Jo Adell",
            "id": 666176,
            "batSide": "R",
            "position": "RF"
          },
          {
            "name": "Jorge Soler",
            "id": 624585,
            "batSide": "R",
            "position": "DH"
          },
          {
            "name": "Wade Meckler",
            "id": 685133,
            "batSide": "L",
            "position": "LF"
          },
          {
            "name": "Denzer Guzman",
            "id": 694203,
            "batSide": "R",
            "position": "3B"
          },
          {
            "name": "Donovan Walton",
            "id": 622268,
            "batSide": "L",
            "position": "2B"
          },
          {
            "name": "Logan O'Hoppe",
            "id": 681351,
            "batSide": "R",
            "position": "C"
          },
          {
            "name": "Jose Siri",
            "id": 642350,
            "batSide": "R",
            "position": "CF"
          }
        ],
        "gameId": "BAL/LAA - Bot 1"
      },
      "odds": {
        "draftkings": {
          "top": {
            "oddsPosted": true,
            "noOdds": 140,
            "yesOdds": -190,
            "impliedNSFI": 0.4167,
            "source": "draftkings_nash"
          },
          "bot": {
            "oddsPosted": true,
            "noOdds": 285,
            "yesOdds": -425,
            "impliedNSFI": 0.2597,
            "source": "draftkings_nash"
          }
        }
      }
    },
    {
      "gamePk": 823288,
      "gameTimeUTC": "2026-06-23T02:10:00Z",
      "gameTimeET": "10:10 PM ET",
      "lineupDropET": "6:40 PM ET",
      "lineupComplete": false,
      "homeTeam": "San Diego Padres",
      "awayTeam": "Atlanta Braves",
      "venue": "Petco Park",
      "ballparkKey": "Padres",
      "topInning": {
        "teamBatting": "Atlanta Braves",
        "teamPitching": "San Diego Padres",
        "pitcher": {
          "name": "Michael King",
          "id": 650633,
          "pitchHand": "R"
        },
        "lineup": [],
        "gameId": "ATL/SD - Top 1"
      },
      "botInning": {
        "teamBatting": "San Diego Padres",
        "teamPitching": "Atlanta Braves",
        "pitcher": {
          "name": "Grant Holmes",
          "id": 656550,
          "pitchHand": "R"
        },
        "lineup": [],
        "gameId": "ATL/SD - Bot 1"
      },
      "odds": {
        "draftkings": {
          "top": {
            "oddsPosted": true,
            "noOdds": 170,
            "yesOdds": -240,
            "impliedNSFI": 0.3704,
            "source": "draftkings_nash"
          },
          "bot": {
            "oddsPosted": true,
            "noOdds": 180,
            "yesOdds": -250,
            "impliedNSFI": 0.3571,
            "source": "draftkings_nash"
          }
        }
      }
    }
  ]
}