{
  "date": "2026-06-21",
  "generatedAt": "2026-06-21T20:10:56.663498",
  "simulations": 10000,
  "predictions": [
    {
      "game_id": "BOS/SEA - Top 1",
      "half": "top",
      "pitcher": "Logan Gilbert",
      "batting_team": "Boston Red Sox",
      "pitching_team": "Seattle Mariners",
      "model_prob": 0.2258,
      "implied_prob": 0.2564,
      "ev": -0.0306,
      "ev_category": "negative",
      "dk_no_odds": 290
    },
    {
      "game_id": "BOS/SEA - Bot 1",
      "half": "bot",
      "pitcher": "Payton Tolle",
      "batting_team": "Seattle Mariners",
      "pitching_team": "Boston Red Sox",
      "model_prob": 0.272,
      "implied_prob": 0.303,
      "ev": -0.031,
      "ev_category": "negative",
      "dk_no_odds": 230
    },
    {
      "game_id": "NYM/PHI - Top 1",
      "half": "top",
      "pitcher": "Zack Wheeler",
      "batting_team": "New York Mets",
      "pitching_team": "Philadelphia Phillies",
      "model_prob": 0.2457,
      "implied_prob": 0.274,
      "ev": -0.0283,
      "ev_category": "negative",
      "dk_no_odds": 265
    },
    {
      "game_id": "NYM/PHI - Bot 1",
      "half": "bot",
      "pitcher": "David Peterson",
      "batting_team": "Philadelphia Phillies",
      "pitching_team": "New York Mets",
      "model_prob": 0.3044,
      "implied_prob": 0.3571,
      "ev": -0.0527,
      "ev_category": "negative",
      "dk_no_odds": 180
    }
  ]
}