{
  "date": "2026-05-03",
  "generatedAt": "2026-05-03T16:07:04.043270",
  "simulations": 10000,
  "predictions": [
    {
      "game_id": "TOR/MIN - Top 1",
      "half": "top",
      "pitcher": "Joe Ryan",
      "batting_team": "Toronto Blue Jays",
      "pitching_team": "Minnesota Twins",
      "model_prob": 0.2858,
      "implied_prob": 0.2899,
      "ev": -0.0041,
      "ev_category": "negative",
      "dk_no_odds": 245
    },
    {
      "game_id": "TOR/MIN - Bot 1",
      "half": "bot",
      "pitcher": "Trey Yesavage",
      "batting_team": "Minnesota Twins",
      "pitching_team": "Toronto Blue Jays",
      "model_prob": 0.2897,
      "implied_prob": 0.303,
      "ev": -0.0133,
      "ev_category": "negative",
      "dk_no_odds": 230
    },
    {
      "game_id": "HOU/BOS - Top 1",
      "half": "top",
      "pitcher": "Ranger Suarez",
      "batting_team": "Houston Astros",
      "pitching_team": "Boston Red Sox",
      "model_prob": 0.3426,
      "implied_prob": 0.4348,
      "ev": -0.0922,
      "ev_category": "negative",
      "dk_no_odds": 130
    },
    {
      "game_id": "HOU/BOS - Bot 1",
      "half": "bot",
      "pitcher": "Cody Bolton",
      "batting_team": "Boston Red Sox",
      "pitching_team": "Houston Astros",
      "model_prob": 0.2241,
      "implied_prob": 0.2857,
      "ev": -0.0616,
      "ev_category": "negative",
      "dk_no_odds": 250
    },
    {
      "game_id": "CIN/PIT - Top 1",
      "half": "top",
      "pitcher": "Braxton Ashcraft",
      "batting_team": "Cincinnati Reds",
      "pitching_team": "Pittsburgh Pirates",
      "model_prob": 0.266,
      "implied_prob": 0.2597,
      "ev": 0.0063,
      "ev_category": "marginal",
      "dk_no_odds": 285
    },
    {
      "game_id": "CIN/PIT - Bot 1",
      "half": "bot",
      "pitcher": "Chase Burns",
      "batting_team": "Pittsburgh Pirates",
      "pitching_team": "Cincinnati Reds",
      "model_prob": 0.172,
      "implied_prob": 0.2,
      "ev": -0.028,
      "ev_category": "negative",
      "dk_no_odds": 400
    },
    {
      "game_id": "BAL/NYY - Top 1",
      "half": "top",
      "pitcher": "Max Fried",
      "batting_team": "Baltimore Orioles",
      "pitching_team": "New York Yankees",
      "model_prob": 0.2988,
      "implied_prob": 0.3846,
      "ev": -0.0858,
      "ev_category": "negative",
      "dk_no_odds": 160
    },
    {
      "game_id": "BAL/NYY - Bot 1",
      "half": "bot",
      "pitcher": "Trey Gibson",
      "batting_team": "New York Yankees",
      "pitching_team": "Baltimore Orioles",
      "model_prob": 0.3103,
      "implied_prob": 0.3774,
      "ev": -0.0671,
      "ev_category": "negative",
      "dk_no_odds": 165
    },
    {
      "game_id": "MIL/WSH - Bot 1",
      "half": "bot",
      "pitcher": "Logan Henderson",
      "batting_team": "Washington Nationals",
      "pitching_team": "Milwaukee Brewers",
      "model_prob": 0.2626,
      "implied_prob": 0.2985,
      "ev": -0.0359,
      "ev_category": "negative",
      "dk_no_odds": 235
    },
    {
      "game_id": "SF/TB - Top 1",
      "half": "top",
      "pitcher": "Steven Matz",
      "batting_team": "San Francisco Giants",
      "pitching_team": "Tampa Bay Rays",
      "model_prob": 0.3617,
      "implied_prob": 0.339,
      "ev": 0.0227,
      "ev_category": "marginal",
      "dk_no_odds": 195
    },
    {
      "game_id": "SF/TB - Bot 1",
      "half": "bot",
      "pitcher": "Tyler Mahle",
      "batting_team": "Tampa Bay Rays",
      "pitching_team": "San Francisco Giants",
      "model_prob": 0.3759,
      "implied_prob": 0.4167,
      "ev": -0.0408,
      "ev_category": "negative",
      "dk_no_odds": 140
    },
    {
      "game_id": "PHI/MIA - Top 1",
      "half": "top",
      "pitcher": "Chris Paddack",
      "batting_team": "Philadelphia Phillies",
      "pitching_team": "Miami Marlins",
      "model_prob": 0.3834,
      "implied_prob": 0.3704,
      "ev": 0.013,
      "ev_category": "marginal",
      "dk_no_odds": 170
    },
    {
      "game_id": "PHI/MIA - Bot 1",
      "half": "bot",
      "pitcher": "Jes\u00fas Luzardo",
      "batting_team": "Miami Marlins",
      "pitching_team": "Philadelphia Phillies",
      "model_prob": 0.2838,
      "implied_prob": 0.2817,
      "ev": 0.0021,
      "ev_category": "marginal",
      "dk_no_odds": 255
    },
    {
      "game_id": "LAD/STL - Top 1",
      "half": "top",
      "pitcher": "Dustin May",
      "batting_team": "Los Angeles Dodgers",
      "pitching_team": "St. Louis Cardinals",
      "model_prob": 0.2906,
      "implied_prob": 0.3922,
      "ev": -0.1016,
      "ev_category": "negative",
      "dk_no_odds": 155
    },
    {
      "game_id": "LAD/STL - Bot 1",
      "half": "bot",
      "pitcher": "Justin Wrobleski",
      "batting_team": "St. Louis Cardinals",
      "pitching_team": "Los Angeles Dodgers",
      "model_prob": 0.2842,
      "implied_prob": 0.3774,
      "ev": -0.0932,
      "ev_category": "negative",
      "dk_no_odds": 165
    },
    {
      "game_id": "ARI/CHC - Top 1",
      "half": "top",
      "pitcher": "Matthew Boyd",
      "batting_team": "Arizona Diamondbacks",
      "pitching_team": "Chicago Cubs",
      "model_prob": 0.41,
      "implied_prob": 0.3509,
      "ev": 0.0591,
      "ev_category": "strong",
      "dk_no_odds": 185
    },
    {
      "game_id": "ARI/CHC - Bot 1",
      "half": "bot",
      "pitcher": "Merrill Kelly",
      "batting_team": "Chicago Cubs",
      "pitching_team": "Arizona Diamondbacks",
      "model_prob": 0.3832,
      "implied_prob": 0.5,
      "ev": -0.1168,
      "ev_category": "negative",
      "dk_no_odds": 100
    }
  ]
}